famapy/metamodels/pysat_metamodel/__init__.py
famapy/metamodels/pysat_metamodel/models/__init__.py
famapy/metamodels/pysat_metamodel/models/pysat_model.py
famapy/metamodels/pysat_metamodel/models/txtcnf_model.py
famapy/metamodels/pysat_metamodel/operations/__init__.py
famapy/metamodels/pysat_metamodel/operations/glucose3_commonality.py
famapy/metamodels/pysat_metamodel/operations/glucose3_core_features.py
famapy/metamodels/pysat_metamodel/operations/glucose3_dead_features.py
famapy/metamodels/pysat_metamodel/operations/glucose3_error_detection.py
famapy/metamodels/pysat_metamodel/operations/glucose3_false_optional_features.py
famapy/metamodels/pysat_metamodel/operations/glucose3_filter.py
famapy/metamodels/pysat_metamodel/operations/glucose3_products.py
famapy/metamodels/pysat_metamodel/operations/glucose3_products_number.py
famapy/metamodels/pysat_metamodel/operations/glucose3_valid.py
famapy/metamodels/pysat_metamodel/operations/glucose3_valid_configuration.py
famapy/metamodels/pysat_metamodel/operations/glucose3_valid_product.py
famapy/metamodels/pysat_metamodel/transformations/__init__.py
famapy/metamodels/pysat_metamodel/transformations/cnf_to_pysat.py
famapy/metamodels/pysat_metamodel/transformations/fm_to_pysat.py
famapy_sat-1.0.0.dist-info/METADATA
famapy_sat-1.0.0.dist-info/WHEEL
famapy_sat-1.0.0.dist-info/dependency_links.txt
famapy_sat-1.0.0.dist-info/top_level.txt
famapy_sat-1.0.0.dist-info/RECORD
