Metadata-Version: 2.1
Name: famapy-sat
Version: 1.0.0
Summary: famapy-sat is a plugin to FaMaPy module
Home-page: https://github.com/FaMaPy/pysat_metamodel
Author: Víctor Ramírez de la Corte
Author-email: me@virako.es
License: UNKNOWN
Platform: UNKNOWN
Classifier: Programming Language :: Python :: 3
Classifier: License :: OSI Approved :: GNU General Public License v3 or later (GPLv3+)
Classifier: Operating System :: OS Independent
Requires-Python: >=3.9
Requires-Dist: famapy (~=1.0.0)
Requires-Dist: famapy-fm (~=1.0.0)
Requires-Dist: python-sat (>=0.1.7.dev6)
Provides-Extra: dev
Requires-Dist: pytest ; extra == 'dev'
Requires-Dist: pytest-mock ; extra == 'dev'
Requires-Dist: prospector ; extra == 'dev'
Requires-Dist: mypy ; extra == 'dev'
Requires-Dist: coverage ; extra == 'dev'
